ceryx.py
ceryx-0.2.0.dist-info/METADATA
ceryx-0.2.0.dist-info/WHEEL
ceryx-0.2.0.dist-info/top_level.txt
ceryx-0.2.0.dist-info/RECORD
